textalytics_core/entity_recognition.py
textalytics_core/resources.py
textalytics_core-0.1.2.dist-info/entry_points.txt
textalytics_core-0.1.2.dist-info/WHEEL
textalytics_core-0.1.2.dist-info/METADATA
textalytics_core-0.1.2.dist-info/RECORD
