Metadata-Version: 2.1
Name: textalytics-core
Version: 0.1.2
Summary: core textalytics capabilities
License: MIT
Author: Manoj Bharadwaj
Author-email: manoj@cloudcosmos.tech
Requires-Python: >=3.8,<4.0
Classifier: License :: OSI Approved :: MIT License
Classifier: Programming Language :: Python :: 3
Classifier: Programming Language :: Python :: 3.8
Classifier: Programming Language :: Python :: 3.9
Requires-Dist: pydantic (>=1.8.2,<2.0.0)
